pygsgui/__init__.py
pygsgui/basicTheme.json
pygsgui/core/Event.py
pygsgui/core/FriendMethod.py
pygsgui/core/Function.py
pygsgui/core/ShortCut.py
pygsgui/core/UIManager.py
pygsgui/core/__init__.py
pygsgui/core/utils.py
pygsgui/elements/Button.py
pygsgui/elements/CheckBox.py
pygsgui/elements/ISGUIBasicObject.py
pygsgui/elements/Label.py
pygsgui/elements/Menu.py
pygsgui/elements/RadioButton.py
pygsgui/elements/ToolBar.py
pygsgui/elements/Window.py
pygsgui/elements/__init__.py
pygsgui-1.0.0.dist-info/LICENSE
pygsgui-1.0.0.dist-info/METADATA
pygsgui-1.0.0.dist-info/WHEEL
pygsgui-1.0.0.dist-info/top_level.txt
pygsgui-1.0.0.dist-info/RECORD
