Metadata-Version: 2.1
Name: pygsgui
Version: 1.0.0
Summary: This my first Python Game Super Graphic User Interface!!!
Home-page: https://github.com/StupidDeveloper05/pygsgui
Author: StupidDeveloper05
Author-email: StupidDeveloper05@gmail.com
License: UNKNOWN
Platform: UNKNOWN
Classifier: Programming Language :: Python :: 3
Classifier: License :: OSI Approved :: MIT License
Classifier: Operating System :: OS Independent
Requires-Python: >=3.6
License-File: LICENSE
Requires-Dist: pillow
Requires-Dist: overrides
Requires-Dist: keyboard
